CHANGELOG.txt
LICENCE.txt
MANIFEST.in
README.md
dev_test.py
requirements.txt
setup.py
.history/CHANGELOG_20210404102321.txt
.history/CHANGELOG_20210404102334.txt
.history/LICENCE_20210404102205.txt
.history/LICENCE_20210404102219.txt
.history/dev_test_20210330191553.py
.history/dev_test_20210404093926.py
.history/dev_test_20210404093933.py
.history/dev_test_20210404094002.py
.history/dev_test_20210404094016.py
.history/dev_test_20210404094037.py
.history/dev_test_20210404094043.py
.history/setup_20210325122434.py
.history/setup_20210404092819.py
.history/setup_20210404093233.py
.history/setup_20210404101854.py
.history/setup_20210404101858.py
.history/python_core/python_core_20210331184609.py
.history/python_core/python_core_20210404093537.py
.history/python_core/python_test_pypi_20210404093537.py
.history/python_core/python_test_pypi_20210404093552.py
.history/python_core/python_test_pypi_20210404093600.py
.history/python_core/python_test_pypi_20210404093609.py
.history/python_core/python_test_pypi_20210404093617.py
.history/python_core/python_test_pypi_20210404093621.py
.history/python_core/python_test_pypi_20210404093633.py
.history/python_core/python_test_pypi_20210404093644.py
.history/python_core/python_test_pypi_20210404093656.py
.history/python_core/python_test_pypi_20210404093657.py
.history/python_core/python_test_pypi_20210404093700.py
.history/python_core/python_test_pypi_20210404093701.py
.history/python_core/python_test_pypi_20210404093823.py
.history/python_core/python_test_pypi_20210404093831.py
.history/python_core/exceptions/__init___20210325142007.py
.history/python_core/exceptions/__init___20210404093813.py
.history/python_core/exceptions/exceptions_20210404090523.py
.history/python_core/exceptions/exceptions_20210404093715.py
.history/python_core/exceptions/exceptions_20210404093735.py
.history/python_core/exceptions/exceptions_20210404093739.py
.history/python_core/exceptions/exceptions_20210404093743.py
python_test_pypi.egg-info/PKG-INFO
python_test_pypi.egg-info/SOURCES.txt
python_test_pypi.egg-info/dependency_links.txt
python_test_pypi.egg-info/requires.txt
python_test_pypi.egg-info/top_level.txt
