Metadata-Version: 2.1
Name: python-test-pypi
Version: 0.0.1
Summary: http client             handles all errors             exceptions 
Home-page: https://github.com/N950/test_pypi.git
Author: test user
Author-email: test_user@pptest.com
License: UNKNOWN
Platform: UNKNOWN
Classifier: Programming Language :: Python :: 3.6
Classifier: Intended Audience :: Developers
Classifier: License :: OSI Approved :: MIT License
